hermes/__init__.py
hermes/main.py
hermes_curl-1.0.8.dist-info/METADATA
hermes_curl-1.0.8.dist-info/WHEEL
hermes_curl-1.0.8.dist-info/entry_points.txt
hermes_curl-1.0.8.dist-info/top_level.txt
hermes_curl-1.0.8.dist-info/RECORD
