Metadata-Version: 2.1
Name: hermes-curl
Version: 1.0.8
Summary: Hermes cURL is a lightweight wrapper on top of cURL that provides reusable HTTP request configurations in YAML.
Home-page: https://github.com/newswangerd/hermes-curl
License: UNKNOWN
Platform: UNKNOWN
Requires-Dist: PyYAML (==5.4.1)
